toll_collect.v
module toll_system(
    input clk,
    input reset,
    input vehicle_detected,
    input [1:0] vehicle_type,     // 00=Car, 01=Truck, 10=Bike
    input [15:0] card_balance,    // Balance on user card
    output reg [15:0] new_balance,
    output reg [7:0] toll_deducted,
    output reg gate_open,
    output reg [2:0] state,       // FSM state output
    output reg [7:0] display_msg  // Display output (ASCII code)
);

    // Vehicle Types
    parameter CAR   = 2'b00;
    parameter TRUCK = 2'b01;
    parameter BIKE  = 2'b10;

    // Toll prices
    parameter CAR_TOLL   = 50;
    parameter TRUCK_TOLL = 100;
    parameter BIKE_TOLL  = 20;

    // FSM States
    parameter IDLE      = 3'b000;
    parameter CHECK     = 3'b001;
    parameter BALANCE   = 3'b010;
    parameter DEDUCT    = 3'b011;
    parameter OPEN_GATE = 3'b100;
    parameter DENY      = 3'b101;

    reg [2:0] next_state;

    // FSM state transition
    always @(posedge clk or posedge reset) begin
        if (reset)
            state <= IDLE;
        else
            state <= next_state;
    end

    // FSM next-state logic
    always @(*) begin
        next_state = state;
        case (state)
            IDLE: if (vehicle_detected) next_state = CHECK;
            CHECK: next_state = BALANCE;
            BALANCE: if (card_balance >= toll_deducted) next_state = DEDUCT;
                     else next_state = DENY;
            DEDUCT: next_state = OPEN_GATE;
            OPEN_GATE: next_state = IDLE;
            DENY: next_state = IDLE;
        endcase
    end

    // Output logic
    always @(posedge clk or posedge reset) begin
        if (reset) begin
            toll_deducted <= 0;
            new_balance   <= 0;
            gate_open     <= 0;
            display_msg   <= " "; // blank
        end else begin
            case (state)
                IDLE: begin
                    toll_deducted <= 0;
                    gate_open <= 0;
                    display_msg <= "W"; // Welcome
                end
                CHECK: begin
                    case (vehicle_type)
                        CAR:   toll_deducted <= CAR_TOLL;
                        TRUCK: toll_deducted <= TRUCK_TOLL;
                        BIKE:  toll_deducted <= BIKE_TOLL;
                        default: toll_deducted <= 0;
                    endcase
                    display_msg <= "P"; // Pay toll
                end
                BALANCE: begin
                    display_msg <= "C"; // Checking
                end
                DEDUCT: begin
                    new_balance <= card_balance - toll_deducted;
                    display_msg <= "D"; // Deducting
                end
                OPEN_GATE: begin
                    gate_open <= 1;
                    display_msg <= "O"; // Open
                end
                DENY: begin
                    new_balance <= card_balance;
                    gate_open <= 0;
                    display_msg <= "X"; // Deny
                end
            endcase
        end
    end
endmodule

toll_collect_tb.v
module tb_toll_system;
    reg clk, reset, vehicle_detected;
    reg [1:0] vehicle_type;
    reg [15:0] card_balance;
    wire [15:0] new_balance;
    wire [7:0] toll_deducted;
    wire gate_open;
    wire [2:0] state;
    wire [7:0] display_msg;

    toll_system uut(
        .clk(clk), .reset(reset),
        .vehicle_detected(vehicle_detected),
        .vehicle_type(vehicle_type),
        .card_balance(card_balance),
        .new_balance(new_balance),
        .toll_deducted(toll_deducted),
        .gate_open(gate_open),
        .state(state),
        .display_msg(display_msg)
    );

    always #5 clk = ~clk; // Clock generation

    initial begin
        // GTKWave dump
        $dumpfile("toll_system.vcd");
        $dumpvars(0, tb_toll_system);

        // Console log
        $monitor("Time=%0t | State=%0d | Vehicle=%0b | Toll=%0d | Balance=%0d | NewBalance=%0d | Gate=%b | Display=%c", 
                 $time, state, vehicle_type, toll_deducted, card_balance, new_balance, gate_open, display_msg);

        // Init
        clk = 0; reset = 1; vehicle_detected = 0; vehicle_type = 0; card_balance = 0;
        #10 reset = 0;

        // Test 1: Car with enough balance
        card_balance = 200; vehicle_type = 2'b00; vehicle_detected = 1; #10;
        vehicle_detected = 0; #50;

        // Test 2: Truck with enough balance
        card_balance = new_balance; vehicle_type = 2'b01; vehicle_detected = 1; #10;
        vehicle_detected = 0; #50;

        // Test 3: Bike with NOT enough balance
        card_balance = 10; vehicle_type = 2'b10; vehicle_detected = 1; #10;
        vehicle_detected = 0; #50;

        $finish;
    end
endmodule

toll_system.vcd
$date
	Mon Nov 10 17:07:54 2025
$end
$version
	Icarus Verilog
$end
$timescale
	1s
$end
$scope module tb_toll_system $end
$var wire 8 ! toll_deducted [7:0] $end
$var wire 3 " state [2:0] $end
$var wire 16 # new_balance [15:0] $end
$var wire 1 $ gate_open $end
$var wire 8 % display_msg [7:0] $end
$var reg 16 & card_balance [15:0] $end
$var reg 1 ' clk $end
$var reg 1 ( reset $end
$var reg 1 ) vehicle_detected $end
$var reg 2 * vehicle_type [1:0] $end
$scope module uut $end
$var wire 16 + card_balance [15:0] $end
$var wire 1 ' clk $end
$var wire 1 ( reset $end
$var wire 1 ) vehicle_detected $end
$var wire 2 , vehicle_type [1:0] $end
$var parameter 3 - BALANCE $end
$var parameter 2 . BIKE $end
$var parameter 32 / BIKE_TOLL $end
$var parameter 2 0 CAR $end
$var parameter 32 1 CAR_TOLL $end
$var parameter 3 2 CHECK $end
$var parameter 3 3 DEDUCT $end
$var parameter 3 4 DENY $end
$var parameter 3 5 IDLE $end
$var parameter 3 6 OPEN_GATE $end
$var parameter 2 7 TRUCK $end
$var parameter 32 8 TRUCK_TOLL $end
$var reg 8 9 display_msg [7:0] $end
$var reg 1 $ gate_open $end
$var reg 16 : new_balance [15:0] $end
$var reg 3 ; next_state [2:0] $end
$var reg 3 < state [2:0] $end
$var reg 8 = toll_deducted [7:0] $end
$upscope $end
$upscope $end
$enddefinitions $end
$comment Show the parameter values. $end
$dumpall
b1100100 8
b1 7
b100 6
b0 5
b101 4
b11 3
b1 2
b110010 1
b0 0
b10100 /
b10 .
b10 -
$end
#0
$dumpvars
b0 =
b0 <
b0 ;
b0 :
b100000 9
b0 ,
b0 +
b0 *
0)
1(
0'
b0 &
b100000 %
0$
b0 #
b0 "
b0 !
$end
#5
1'
#10
b1 ;
0'
1)
b11001000 &
b11001000 +
0(
#15
b10 ;
b1 "
b1 <
b1010111 %
b1010111 9
1'
#20
b10 ;
0'
0)
#25
b11 ;
b1010000 %
b1010000 9
b110010 !
b110010 =
b10 "
b10 <
1'
#30
0'
#35
b100 ;
b11 "
b11 <
b1000011 %
b1000011 9
1'
#40
0'
#45
b0 ;
b1000100 %
b1000100 9
b10010110 #
b10010110 :
b100 "
b100 <
1'
#50
0'
#55
b0 "
b0 <
b1001111 %
b1001111 9
1$
1'
#60
0'
#65
b1010111 %
b1010111 9
0$
b0 !
b0 =
1'
#70
b1 ;
0'
1)
b1 *
b1 ,
b10010110 &
b10010110 +
#75
b10 ;
b1 "
b1 <
1'
#80
b10 ;
0'
0)
#85
b11 ;
b1010000 %
b1010000 9
b1100100 !
b1100100 =
b10 "
b10 <
1'
#90
0'
#95
b100 ;
b11 "
b11 <
b1000011 %
b1000011 9
1'
#100
0'
#105
b0 ;
b1000100 %
b1000100 9
b110010 #
b110010 :
b100 "
b100 <
1'
#110
0'
#115
b0 "
b0 <
b1001111 %
b1001111 9
1$
1'
#120
0'
#125
b1010111 %
b1010111 9
0$
b0 !
b0 =
1'
#130
b1 ;
0'
1)
b10 *
b10 ,
b1010 &
b1010 +
#135
b10 ;
b1 "
b1 <
1'
#140
b10 ;
0'
0)
#145
b101 ;
b1010000 %
b1010000 9
b10100 !
b10100 =
b10 "
b10 <
1'
#150
0'
#155
b0 ;
b101 "
b101 <
b1000011 %
b1000011 9
1'
#160
0'
#165
b1011000 %
b1011000 9
b1010 #
b1010 :
b0 "
b0 <
1'
#170
0'
#175
b1010111 %
b1010111 9
b0 !
b0 =
1'
